humg.py
htr_united_metadata_generator-1.0.4.dist-info/LICENSE
htr_united_metadata_generator-1.0.4.dist-info/METADATA
htr_united_metadata_generator-1.0.4.dist-info/WHEEL
htr_united_metadata_generator-1.0.4.dist-info/entry_points.txt
htr_united_metadata_generator-1.0.4.dist-info/top_level.txt
htr_united_metadata_generator-1.0.4.dist-info/RECORD
