Metadata-Version: 2.1
Name: htr-united-metadata-generator
Version: 1.0.4
Summary: A cool tool to generate report for HTR repositories
Home-page: https://github.com/htr-united/htr-united-metadata-generator
Author: Thibault Clerice
License: MIT
Platform: UNKNOWN
Classifier: License :: OSI Approved :: MIT License
Classifier: Programming Language :: Python
Classifier: Programming Language :: Python :: 3
Classifier: Programming Language :: Python :: 3.6
Classifier: Programming Language :: Python :: Implementation :: CPython
Classifier: Programming Language :: Python :: Implementation :: PyPy
Classifier: Topic :: Text Processing :: Linguistic
Requires-Python: >=3.6.0
License-File: LICENSE
Requires-Dist: click (>=8.0.1)
Requires-Dist: lxml (>=4.6.3)
Requires-Dist: tabulate (>=0.8.9)
